debianbts/__init__.py
debianbts/__main__.py
debianbts/debianbts.py
debianbts/py.typed
debianbts/version.py
python_debianbts-4.1.1.dist-info/LICENSE
python_debianbts-4.1.1.dist-info/METADATA
python_debianbts-4.1.1.dist-info/WHEEL
python_debianbts-4.1.1.dist-info/entry_points.txt
python_debianbts-4.1.1.dist-info/top_level.txt
python_debianbts-4.1.1.dist-info/RECORD
