Metadata-Version: 2.1
Name: python-debianbts
Version: 4.1.1
Summary: Python interface to Debian's Bug Tracking System
Author-email: Bastian Venthur <venthur@debian.org>
License: MIT License
Project-URL: Documentation, https://python-debianbts.readthedocs.io/
Project-URL: Source, https://github.com/venthur/python-debianbts
Project-URL: Changelog, https://github.com/venthur/python-debianbts/blob/master/CHANGELOG.md
Classifier: Development Status :: 5 - Production/Stable
Classifier: Intended Audience :: Developers
Classifier: License :: OSI Approved :: MIT License
Classifier: Programming Language :: Python :: 3
Classifier: Topic :: Software Development :: Bug Tracking
Requires-Python: <4,>=3.8
License-File: LICENSE
Provides-Extra: dev
Requires-Dist: build; extra == "dev"
Requires-Dist: mkdocs; extra == "dev"
Requires-Dist: mkdocs-material; extra == "dev"
Requires-Dist: mkdocstrings[python]; extra == "dev"
Requires-Dist: pytest; extra == "dev"
Requires-Dist: pytest-cov; extra == "dev"
Requires-Dist: pytest-xdist; extra == "dev"
Requires-Dist: ruff; extra == "dev"
Requires-Dist: wheel; extra == "dev"
Requires-Dist: twine; extra == "dev"
Requires-Dist: mypy; extra == "dev"
